op_registration/.env
op_registration/GOPregister.py
op_registration/OP_registration.py
op_registration/__init__.py
op_registration/logs/log_2025-05-01_13-56-20.log
op_registration/logs/log_2025-05-01_13-57-09.log
op_registration/logs/log_2025-05-01_14-22-27.log
op_registration/logs/log_2025-05-01_14-23-52.log
op_registration/logs/log_2025-05-01_14-25-31.log
op_registration/logs/log_2025-05-01_14-25-52.log
op_registration/logs/log_2025-05-01_14-27-58.log
op_registration/logs/log_2025-05-01_14-28-30.log
op_registration/logs/log_2025-05-01_14-30-08.log
op_registration/logs/log_2025-05-01_14-30-29.log
op_registration/logs/log_2025-05-01_14-30-45.log
op_registration/logs/log_2025-05-01_14-31-09.log
op_registration/logs/log_2025-05-01_14-35-28.log
op_registration/logs/log_2025-05-01_14-35-44.log
op_registration/logs/log_2025-05-01_14-36-14.log
op_registration/logs/log_2025-05-01_14-40-32.log
op_registration/logs/log_2025-05-01_14-40-42.log
op_registration/logs/log_2025-05-01_14-42-00.log
op_registration/logs/log_2025-05-01_14-43-00.log
op_registration/logs/log_2025-05-01_14-43-25.log
op_registration/logs/log_2025-05-01_14-48-41.log
op_registration/logs/log_2025-05-01_14-50-09.log
op_registration/logs/log_2025-05-01_14-52-54.log
op_registration/logs/log_2025-05-01_14-53-30.log
op_registration/logs/log_2025-05-01_14-54-03.log
op_registration/logs/log_2025-05-01_14-54-13.log
op_registration/logs/log_2025-05-01_14-54-34.log
op_registration/logs/log_2025-05-01_14-54-52.log
op_registration/logs/log_2025-05-01_14-56-32.log
op_registration/logs/log_2025-05-01_14-57-00.log
op_registration/logs/log_2025-05-01_14-57-20.log
op_registration/logs/log_2025-05-01_14-58-23.log
op_registration/logs/log_2025-05-01_14-59-08.log
op_registration/logs/log_2025-05-01_14-59-34.log
op_registration/logs/log_2025-05-01_15-15-46.log
op_registration/logs/log_2025-05-01_15-17-01.log
op_registration/logs/log_2025-05-01_15-17-32.log
op_registration/logs/log_2025-05-01_15-19-52.log
op_registration-0.1.0.dist-info/METADATA
op_registration-0.1.0.dist-info/WHEEL
op_registration-0.1.0.dist-info/entry_points.txt
op_registration-0.1.0.dist-info/RECORD
