Metadata-Version: 2.3
Name: op-registration
Version: 0.1.0
Summary: 
Author: Wilson
Author-email: wilson.diant@gmail.com
Requires-Python: >=3.9,<4.0
Classifier: Programming Language :: Python :: 3
Classifier: Programming Language :: Python :: 3.9
Classifier: Programming Language :: Python :: 3.10
Classifier: Programming Language :: Python :: 3.11
Classifier: Programming Language :: Python :: 3.12
Classifier: Programming Language :: Python :: 3.13
Requires-Dist: click (>=8.1.8,<9.0.0)
Requires-Dist: dotenv (>=0.9.9,<0.10.0)
Requires-Dist: inquirerpy (>=0.3.4,<0.4.0)
Requires-Dist: playwright (>=1.51.0,<2.0.0)
Requires-Dist: pync (>=2.0.3,<3.0.0)
Requires-Dist: schedule (>=1.2.2,<2.0.0)
